[{"lat":"37.47246189","long":"126.8391794","imageIndex":4,"items":[{"name":"맛드림","tel":"02-2617-3805","addr":"경기도 광명시 옥길동 95-2번지","indutype":"일반휴게음식 - 일반한식","category":"restaurant"}]},{"lat":"37.46248677","long":"126.8320462","imageIndex":4,"items":[{"name":"모녀가든","tel":"02-2612-1282","addr":"경기도 광명시 옥길동 410-6번지 1층","indutype":"일반휴게음식 - 일반한식","category":"restaurant"}]},{"lat":"37.46971033","long":"126.8431871","imageIndex":4,"items":[{"name":"신의주찹쌀순대","tel":"02-2683-8255","addr":"경기도 광명시 옥길동 21-1번지 1층","indutype":"일반휴게음식 - 일반한식","category":"restaurant"}]},{"lat":"37.4611253","long":"126.8313825","imageIndex":4,"items":[{"name":"오생도토리묵집","tel":"02-2619-3215","addr":"경기도 광명시 옥길동 350-1번지 1층","indutype":"일반휴게음식 - 일반한식","category":"restaurant"}]},{"lat":"37.47503852","long":"126.8390155","imageIndex":4,"items":[{"name":"옥길두루치기","tel":"02-2612-2170","addr":"경기도 광명시 옥길동 100-7번지 1층","indutype":"일반휴게음식 - 일반한식","category":"restaurant"}]},{"lat":"37.46982264","long":"126.8396599","imageIndex":4,"items":[{"name":"황제 쟁반 수타면","tel":"02-2686-5513","addr":"경기도 광명시 옥길동 44-7번지 1층","indutype":"일반휴게음식 - 중국식","category":"restaurant"}]}]