[{"REFINE_WGS84_LAT":"37.725650913","REFINE_WGS84_LOGT":"127.04918413","CMPNM_NM":"120% COOL(회룡점)","TELNO":"031-836-0120","REFINE_LOTNO_ADDR":"경기도 의정부시 호원동 423번지 대명빌딩 201호","INDUTYPE_NM":"보건위생 - 미용원"},{"REFINE_WGS84_LAT":"37.709352879","REFINE_WGS84_LOGT":"127.04834613","CMPNM_NM":"120%쿨(망월사점)","TELNO":"031-826-5120","REFINE_LOTNO_ADDR":"경기도 의정부시 호원동 459번지 신일엘리시움 상가 110호","INDUTYPE_NM":"보건위생 - 미용원"},{"REFINE_WGS84_LAT":"37.727265774","REFINE_WGS84_LOGT":"127.0433547","CMPNM_NM":"B2.준헤어","TELNO":"031-879-0449","REFINE_LOTNO_ADDR":"경기도 의정부시 호원동 327-6 호원상가104호,114호","INDUTYPE_NM":"보건위생 - 미용원"},{"REFINE_WGS84_LAT":"37.706848089","REFINE_WGS84_LOGT":"127.04865079","CMPNM_NM":"H헤어","TELNO":"031-837-2356","REFINE_LOTNO_ADDR":"경기도 의정부시 호원동 463-13번지 1층","INDUTYPE_NM":"보건위생 - 미용원"},{"REFINE_WGS84_LAT":"37.724516968","REFINE_WGS84_LOGT":"127.04584863","CMPNM_NM":"고수헤어","TELNO":"","REFINE_LOTNO_ADDR":"경기도 의정부시 호원동 51-2번지 303호","INDUTYPE_NM":"보건위생 - 미용원"},{"REFINE_WGS84_LAT":"37.708154801","REFINE_WGS84_LOGT":"127.04782374","CMPNM_NM":"기분좋은날 헤어샵","TELNO":"031-837-8980","REFINE_LOTNO_ADDR":"경기도 의정부시 호원동 464-3번지 1층 102호","INDUTYPE_NM":"보건위생 - 미용원"},{"REFINE_WGS84_LAT":"37.722742896","REFINE_WGS84_LOGT":"127.04354506","CMPNM_NM":"긴스헤어 (GIN'S HAIR)","TELNO":"031-855-3690","REFINE_LOTNO_ADDR":"경기도 의정부시 호원동 309-66번지 드림캐슬 B104호","INDUTYPE_NM":"보건위생 - 미용원"},{"REFINE_WGS84_LAT":"37.728130003","REFINE_WGS84_LOGT":"127.04531758","CMPNM_NM":"꽃머리","TELNO":"031-837-8228","REFINE_LOTNO_ADDR":"경기도 의정부시 호원동 341-6번지 104호","INDUTYPE_NM":"보건위생 - 미용원"},{"REFINE_WGS84_LAT":"37.726652268","REFINE_WGS84_LOGT":"127.04577046","CMPNM_NM":"나이스가이","TELNO":"031-873-0487","REFINE_LOTNO_ADDR":"경기도 의정부시 호원동 332-1번지","INDUTYPE_NM":"보건위생 - 미용원"},{"REFINE_WGS84_LAT":"37.707244552","REFINE_WGS84_LOGT":"127.04854897","CMPNM_NM":"네이처 망월사점","TELNO":"031-873-3345","REFINE_LOTNO_ADDR":"경기도 의정부시 호원동 463-18번지","INDUTYPE_NM":"보건위생 - 미용원"},{"REFINE_WGS84_LAT":"37.726317317","REFINE_WGS84_LOGT":"127.04995588","CMPNM_NM":"네이처헤어회룡점","TELNO":"031-837-3387","REFINE_LOTNO_ADDR":"경기도 의정부시 호원동 418-3번지 105호","INDUTYPE_NM":"보건위생 - 미용원"},{"REFINE_WGS84_LAT":"37.728150061","REFINE_WGS84_LOGT":"127.03921484","CMPNM_NM":"뉴욕헤어","TELNO":"031-852-5012","REFINE_LOTNO_ADDR":"경기도 의정부시 호원동 377-12번지 1층","INDUTYPE_NM":"보건위생 - 미용원"},{"REFINE_WGS84_LAT":"37.708271926","REFINE_WGS84_LOGT":"127.04782382","CMPNM_NM":"다미머리작","TELNO":"031-877-3470","REFINE_LOTNO_ADDR":"경기도 의정부시 호원동 464-2번지 2층","INDUTYPE_NM":"보건위생 - 미용원"},{"REFINE_WGS84_LAT":"37.703964881","REFINE_WGS84_LOGT":"127.04898921","CMPNM_NM":"댕기머리방","TELNO":"031-879-4092","REFINE_LOTNO_ADDR":"경기도 의정부시 호원동 467아이파크호원상가107","INDUTYPE_NM":"보건위생 - 미용원"},{"REFINE_WGS84_LAT":"37.72623786","REFINE_WGS84_LOGT":"127.04567948","CMPNM_NM":"돌체헤어","TELNO":"031-879-0310","REFINE_LOTNO_ADDR":"경기도 의정부시 호원동 10-52번지 외1필지 진원빌라 상가 나동 102호","INDUTYPE_NM":"보건위생 - 미용원"},{"REFINE_WGS84_LAT":"37.728490227","REFINE_WGS84_LOGT":"127.04576018","CMPNM_NM":"둘이두리","TELNO":"031-826-5491","REFINE_LOTNO_ADDR":"경기도 의정부시 호원동 343번지 호원프라자 107호","INDUTYPE_NM":"보건위생 - 미용원"},{"REFINE_WGS84_LAT":"37.714155202","REFINE_WGS84_LOGT":"127.04781603","CMPNM_NM":"라데팡스헤어","TELNO":"031-871-6229","REFINE_LOTNO_ADDR":"경기도 의정부시 호원동 450번지 미소프라자 103호","INDUTYPE_NM":"보건위생 - 미용원"},{"REFINE_WGS84_LAT":"37.723570674","REFINE_WGS84_LOGT":"127.04663073","CMPNM_NM":"라브리지의정부(회룡역점)","TELNO":"031-859-5821","REFINE_LOTNO_ADDR":"경기도 의정부시 호원동 50-17번지 2층","INDUTYPE_NM":"보건위생 - 미용원"},{"REFINE_WGS84_LAT":"37.71629061","REFINE_WGS84_LOGT":"127.04746573","CMPNM_NM":"라비살롱","TELNO":"031-826-5333","REFINE_LOTNO_ADDR":"경기도 의정부시 호원동 442-3번지 1층","INDUTYPE_NM":"보건위생 - 미용원"},{"REFINE_WGS84_LAT":"37.70856964","REFINE_WGS84_LOGT":"127.04676934","CMPNM_NM":"라썸헤어","TELNO":"031-826-3887","REFINE_LOTNO_ADDR":"경기도 의정부시 호원동 119-138번지 신일스카이빌 101호","INDUTYPE_NM":"보건위생 - 미용원"},{"REFINE_WGS84_LAT":"37.727184499","REFINE_WGS84_LOGT":"127.04389913","CMPNM_NM":"라썸헤어뷰티컴퍼니 범골역점","TELNO":"031-878-1010","REFINE_LOTNO_ADDR":"경기도 의정부시 호원동 327-12번지 2층","INDUTYPE_NM":"보건위생 - 미용원"},{"REFINE_WGS84_LAT":"37.704181709","REFINE_WGS84_LOGT":"127.04743579","CMPNM_NM":"라움헤어","TELNO":"031-825-5055","REFINE_LOTNO_ADDR":"경기도 의정부시 호원동 468-4번지 근린생활시설 1동 7호","INDUTYPE_NM":"보건위생 - 미용원"},{"REFINE_WGS84_LAT":"37.728373677","REFINE_WGS84_LOGT":"127.04414934","CMPNM_NM":"라움헤어","TELNO":"031-9350-8261","REFINE_LOTNO_ADDR":"경기도 의정부시 호원동 341-31번지 1층","INDUTYPE_NM":"보건위생 - 미용원"},{"REFINE_WGS84_LAT":"37.724039649","REFINE_WGS84_LOGT":"127.04532659","CMPNM_NM":"레드 스토리","TELNO":"031-837-3563","REFINE_LOTNO_ADDR":"경기도 의정부시 호원동 312-1번지 2층 일부","INDUTYPE_NM":"보건위생 - 미용원"},{"REFINE_WGS84_LAT":"37.724462145","REFINE_WGS84_LOGT":"127.04790165","CMPNM_NM":"레드헤어","TELNO":"031-821-3575","REFINE_LOTNO_ADDR":"경기도 의정부시 호원동 427-4번지 2층","INDUTYPE_NM":"보건위생 - 미용원"},{"REFINE_WGS84_LAT":"37.729375585","REFINE_WGS84_LOGT":"127.03848945","CMPNM_NM":"로즈헤어샵","TELNO":"031-877-6177","REFINE_LOTNO_ADDR":"경기도 의정부시 호원동 367-11번지 1층","INDUTYPE_NM":"보건위생 - 미용원"},{"REFINE_WGS84_LAT":"37.723958179","REFINE_WGS84_LOGT":"127.04638142","CMPNM_NM":"리안헤어","TELNO":"031-837-9128","REFINE_LOTNO_ADDR":"경기도 의정부시 호원동 50-2번지 회룡타운 1층 110호","INDUTYPE_NM":"보건위생 - 미용원"},{"REFINE_WGS84_LAT":"37.722039928","REFINE_WGS84_LOGT":"127.04417986","CMPNM_NM":"리즈헤어","TELNO":"031-837-0908","REFINE_LOTNO_ADDR":"경기도 의정부시 호원동 309-1번지","INDUTYPE_NM":"보건위생 - 미용원"},{"REFINE_WGS84_LAT":"37.71379442","REFINE_WGS84_LOGT":"127.04884786","CMPNM_NM":"머리 마을 미","TELNO":"031-872-5382","REFINE_LOTNO_ADDR":"경기도 의정부시 호원동 451-6번지 1층","INDUTYPE_NM":"보건위생 - 미용원"},{"REFINE_WGS84_LAT":"37.729067414","REFINE_WGS84_LOGT":"127.04414973","CMPNM_NM":"머리끄댕이","TELNO":"031-826-2611","REFINE_LOTNO_ADDR":"경기도 의정부시 호원동 345-5번지 1층","INDUTYPE_NM":"보건위생 - 미용원"},{"REFINE_WGS84_LAT":"37.727851435","REFINE_WGS84_LOGT":"127.04324158","CMPNM_NM":"머리못하는집","TELNO":"070-8276-6443","REFINE_LOTNO_ADDR":"경기도 의정부시 호원동 326-6번지 화성프라자 119호","INDUTYPE_NM":"보건위생 - 미용원"},{"REFINE_WGS84_LAT":"37.707100464","REFINE_WGS84_LOGT":"127.04837878","CMPNM_NM":"멋찐남자","TELNO":"031-836-0410","REFINE_LOTNO_ADDR":"경기도 의정부시 호원동 463-21번지 1층","INDUTYPE_NM":"보건위생 - 미용원"},{"REFINE_WGS84_LAT":"37.70963305","REFINE_WGS84_LOGT":"127.04602149","CMPNM_NM":"메카(MECA)헤어","TELNO":"031-897-2888","REFINE_LOTNO_ADDR":"경기도 의정부시 호원동 117-1번지 인디안헤드외국인학교 104호","INDUTYPE_NM":"보건위생 - 미용원"},{"REFINE_WGS84_LAT":"37.713129218","REFINE_WGS84_LOGT":"127.04479867","CMPNM_NM":"묘정헤어","TELNO":"031-826-0242","REFINE_LOTNO_ADDR":"경기도 의정부시 호원동 257-1번지 1층","INDUTYPE_NM":"보건위생 - 미용원"},{"REFINE_WGS84_LAT":"37.721986204","REFINE_WGS84_LOGT":"127.04321572","CMPNM_NM":"미쯔다니미용실","TELNO":"031-873-1570","REFINE_LOTNO_ADDR":"경기도 의정부시 호원동 309-24번지 1층 102호","INDUTYPE_NM":"보건위생 - 미용원"},{"REFINE_WGS84_LAT":"37.720903145","REFINE_WGS84_LOGT":"127.04845527","CMPNM_NM":"바야흐로 봄","TELNO":"","REFINE_LOTNO_ADDR":"경기도 의정부시 호원동 431-1번지 2층 일부","INDUTYPE_NM":"보건위생 - 미용원"},{"REFINE_WGS84_LAT":"37.707073188","REFINE_WGS84_LOGT":"127.04901381","CMPNM_NM":"바우헤어","TELNO":"070-7630-6969","REFINE_LOTNO_ADDR":"경기도 의정부시 호원동 462-23번지 1층","INDUTYPE_NM":"보건위생 - 미용원"},{"REFINE_WGS84_LAT":"37.728571481","REFINE_WGS84_LOGT":"127.04529514","CMPNM_NM":"박소현헤어샵","TELNO":"031-875-3730","REFINE_LOTNO_ADDR":"경기도 의정부시 호원동 342-7번지","INDUTYPE_NM":"보건위생 - 미용원"},{"REFINE_WGS84_LAT":"37.705271521","REFINE_WGS84_LOGT":"127.04835498","CMPNM_NM":"뷰티풀데이","TELNO":"","REFINE_LOTNO_ADDR":"경기도 의정부시 호원동 466-12번지 1층 101호","INDUTYPE_NM":"보건위생 - 미용원"},{"REFINE_WGS84_LAT":"37.70599165","REFINE_WGS84_LOGT":"127.04998838","CMPNM_NM":"블레싱헤어","TELNO":"070-8118-2434","REFINE_LOTNO_ADDR":"경기도 의정부시 호원동 121번지 건영 상가 108호","INDUTYPE_NM":"보건위생 - 미용원"},{"REFINE_WGS84_LAT":"37.725876436","REFINE_WGS84_LOGT":"127.04845832","CMPNM_NM":"블루클럽회룡역점","TELNO":"031-837-2210","REFINE_LOTNO_ADDR":"경기도 의정부시 호원동 417-3번지 전원빌딩 102호","INDUTYPE_NM":"보건위생 - 미용원"},{"REFINE_WGS84_LAT":"37.729681492","REFINE_WGS84_LOGT":"127.03985083","CMPNM_NM":"블링블링헤어","TELNO":"031-822-8804","REFINE_LOTNO_ADDR":"경기도 의정부시 호원동 363-6번지 101호","INDUTYPE_NM":"보건위생 - 미용원"},{"REFINE_WGS84_LAT":"37.726436272","REFINE_WGS84_LOGT":"127.04512378","CMPNM_NM":"사랑헤어칼라","TELNO":"031-877-6989","REFINE_LOTNO_ADDR":"경기도 의정부시 호원동 332번지 서왕프라자 1층 111호","INDUTYPE_NM":"보건위생 - 미용원"},{"REFINE_WGS84_LAT":"37.709352879","REFINE_WGS84_LOGT":"127.04834613","CMPNM_NM":"산리쯔헤어","TELNO":"031-846-7829","REFINE_LOTNO_ADDR":"경기도 의정부시 호원동 459번지 신일엘리시움 상가 123호","INDUTYPE_NM":"보건위생 - 미용원"},{"REFINE_WGS84_LAT":"37.70515444","REFINE_WGS84_LOGT":"127.04824151","CMPNM_NM":"살롱드. 미","TELNO":"031-877-2736","REFINE_LOTNO_ADDR":"경기도 의정부시 호원동 466-11번지 북촉1칸","INDUTYPE_NM":"보건위생 - 미용원"},{"REFINE_WGS84_LAT":"37.722211521","REFINE_WGS84_LOGT":"127.04298899","CMPNM_NM":"샤롱드.미","TELNO":"031-873-2525","REFINE_LOTNO_ADDR":"경기도 의정부시 호원동 309-80번지 아름들이마트 104호","INDUTYPE_NM":"보건위생 - 미용원"},{"REFINE_WGS84_LAT":"37.727266889","REFINE_WGS84_LOGT":"127.03996306","CMPNM_NM":"샴푸헤어","TELNO":"031-871-2234","REFINE_LOTNO_ADDR":"경기도 의정부시 호원동 339-19번지","INDUTYPE_NM":"보건위생 - 미용원"},{"REFINE_WGS84_LAT":"37.727852849","REFINE_WGS84_LOGT":"127.03887439","CMPNM_NM":"샹스헤어","TELNO":"031-874-7467","REFINE_LOTNO_ADDR":"경기도 의정부시 호원동 377-1번지","INDUTYPE_NM":"보건위생 - 미용원"},{"REFINE_WGS84_LAT":"37.723824078","REFINE_WGS84_LOGT":"127.04345491","CMPNM_NM":"소호헤어","TELNO":"031-837-5660","REFINE_LOTNO_ADDR":"경기도 의정부시 호원동 313-6번지 2층","INDUTYPE_NM":"보건위생 - 미용원"},{"REFINE_WGS84_LAT":"37.727931793","REFINE_WGS84_LOGT":"127.04531746","CMPNM_NM":"수향헤어","TELNO":"031-855-9330","REFINE_LOTNO_ADDR":"경기도 의정부시 호원동 6-2번지","INDUTYPE_NM":"보건위생 - 미용원"},{"REFINE_WGS84_LAT":"37.728931753","REFINE_WGS84_LOGT":"127.04560162","CMPNM_NM":"수현헤어뱅크","TELNO":"070-8699-6731","REFINE_LOTNO_ADDR":"경기도 의정부시 호원동 344번지 1층","INDUTYPE_NM":"보건위생 - 미용원"},{"REFINE_WGS84_LAT":"37.708181652","REFINE_WGS84_LOGT":"127.04828872","CMPNM_NM":"스타일을 찾다","TELNO":"031-877-2203","REFINE_LOTNO_ADDR":"경기도 의정부시 호원동 460-23번지 2층","INDUTYPE_NM":"보건위생 - 미용원"},{"REFINE_WGS84_LAT":"37.730546332","REFINE_WGS84_LOGT":"127.04010082","CMPNM_NM":"시네마헤어","TELNO":"031-111-1111","REFINE_LOTNO_ADDR":"경기도 의정부시 호원동 357-12번지","INDUTYPE_NM":"보건위생 - 미용원"},{"REFINE_WGS84_LAT":"37.721796473","REFINE_WGS84_LOGT":"127.0447355","CMPNM_NM":"썬헤어(Sun hair)","TELNO":"031-873-4015","REFINE_LOTNO_ADDR":"경기도 의정부시 호원동 311-10번지","INDUTYPE_NM":"보건위생 - 미용원"},{"REFINE_WGS84_LAT":"37.708020413","REFINE_WGS84_LOGT":"127.04579374","CMPNM_NM":"씨앤씨 (c&c)헤어홀릭","TELNO":"031-872-7811","REFINE_LOTNO_ADDR":"경기도 의정부시 호원동 119-250번지 1층","INDUTYPE_NM":"보건위생 - 미용원"},{"REFINE_WGS84_LAT":"37.706965524","REFINE_WGS84_LOGT":"127.04784571","CMPNM_NM":"아름다운머리","TELNO":"031-836-3621","REFINE_LOTNO_ADDR":"경기도 의정부시 호원동 464-16번지","INDUTYPE_NM":"보건위생 - 미용원"},{"REFINE_WGS84_LAT":"37.727374257","REFINE_WGS84_LOGT":"127.0422658","CMPNM_NM":"엘뷰티헤어","TELNO":"031-879-2490","REFINE_LOTNO_ADDR":"경기도 의정부시 호원동 322-5 호원가든2차상가 106","INDUTYPE_NM":"보건위생 - 미용원"},{"REFINE_WGS84_LAT":"37.730906629","REFINE_WGS84_LOGT":"127.04037325","CMPNM_NM":"여니헤어","TELNO":"031-877-5844","REFINE_LOTNO_ADDR":"경기도 의정부시 호원동 357-4번지 1층","INDUTYPE_NM":"보건위생 - 미용원"},{"REFINE_WGS84_LAT":"37.712957465","REFINE_WGS84_LOGT":"127.04637499","CMPNM_NM":"영주헤어","TELNO":"","REFINE_LOTNO_ADDR":"경기도 의정부시 호원동 86-1번지 1층","INDUTYPE_NM":"보건위생 - 미용원"},{"REFINE_WGS84_LAT":"37.725903721","REFINE_WGS84_LOGT":"127.04778909","CMPNM_NM":"오 헤어(O'Hair)","TELNO":"031-837-2235","REFINE_LOTNO_ADDR":"경기도 의정부시 호원동 414-9번지 203,204호","INDUTYPE_NM":"보건위생 - 미용원"},{"REFINE_WGS84_LAT":"37.725903721","REFINE_WGS84_LOGT":"127.04778909","CMPNM_NM":"오 헤어(O'Hair)","TELNO":"031-837-2235","REFINE_LOTNO_ADDR":"경기도 의정부시 호원동 414-9번지 203,204","INDUTYPE_NM":"보건위생 - 미용원"},{"REFINE_WGS84_LAT":"37.707685851","REFINE_WGS84_LOGT":"127.04899151","CMPNM_NM":"오땡큐염색전문점","TELNO":"031-877-3678","REFINE_LOTNO_ADDR":"경기도 의정부시 호원동 462번지 1층","INDUTYPE_NM":"보건위생 - 미용원"},{"REFINE_WGS84_LAT":"37.725903721","REFINE_WGS84_LOGT":"127.04778909","CMPNM_NM":"오헤어 위드 세인(O hair with sein)","TELNO":"031-1111-1111","REFINE_LOTNO_ADDR":"경기도 의정부시 호원동 414-9번지 106호","INDUTYPE_NM":"보건위생 - 미용원"},{"REFINE_WGS84_LAT":"37.708460427","REFINE_WGS84_LOGT":"127.04962705","CMPNM_NM":"우리헤어","TELNO":"031-837-0817","REFINE_LOTNO_ADDR":"경기도 의정부시 호원동 461번지 신일유토빌플러스 상가동 103호","INDUTYPE_NM":"보건위생 - 미용원"},{"REFINE_WGS84_LAT":"37.726734294","REFINE_WGS84_LOGT":"127.04310486","CMPNM_NM":"유디헤어","TELNO":"031-877-6261","REFINE_LOTNO_ADDR":"경기도 의정부시 호원동 320-1번지","INDUTYPE_NM":"보건위생 - 미용원"},{"REFINE_WGS84_LAT":"37.715434256","REFINE_WGS84_LOGT":"127.04862204","CMPNM_NM":"유진헤어살롱","TELNO":"031-836-7627","REFINE_LOTNO_ADDR":"경기도 의정부시 호원동 445-5번지 우성빌딩 1층","INDUTYPE_NM":"보건위생 - 미용원"},{"REFINE_WGS84_LAT":"37.706965006","REFINE_WGS84_LOGT":"127.04918385","CMPNM_NM":"윤미용실","TELNO":"031-859-8769","REFINE_LOTNO_ADDR":"경기도 의정부시 호원동 462-33번지 1층","INDUTYPE_NM":"보건위생 - 미용원"},{"REFINE_WGS84_LAT":"37.706073359","REFINE_WGS84_LOGT":"127.04840083","CMPNM_NM":"이레미용실","TELNO":"031-878-2171","REFINE_LOTNO_ADDR":"경기도 의정부시 호원동 466번지 아르쥬 1층 104호","INDUTYPE_NM":"보건위생 - 미용원"},{"REFINE_WGS84_LAT":"37.728373449","REFINE_WGS84_LOGT":"127.04479592","CMPNM_NM":"이루다헤어","TELNO":"031-875-3644","REFINE_LOTNO_ADDR":"경기도 의정부시 호원동 341-49번지 1층","INDUTYPE_NM":"보건위생 - 미용원"},{"REFINE_WGS84_LAT":"37.728463366","REFINE_WGS84_LOGT":"127.04529508","CMPNM_NM":"이수진헤어","TELNO":"031-872-5382","REFINE_LOTNO_ADDR":"경기도 의정부시 호원동 342-11번지 1층","INDUTYPE_NM":"보건위생 - 미용원"},{"REFINE_WGS84_LAT":"37.711794682","REFINE_WGS84_LOGT":"127.04782594","CMPNM_NM":"이오헤어(IO)","TELNO":"031-821-2844","REFINE_LOTNO_ADDR":"경기도 의정부시 호원동 455-8번지 103호","INDUTYPE_NM":"보건위생 - 미용원"},{"REFINE_WGS84_LAT":"37.726436071","REFINE_WGS84_LOGT":"127.04567959","CMPNM_NM":"자르젠헤어","TELNO":"","REFINE_LOTNO_ADDR":"경기도 의정부시 호원동 332-5번지 진원빌라 상가 103호","INDUTYPE_NM":"보건위생 - 미용원"},{"REFINE_WGS84_LAT":"37.706938044","REFINE_WGS84_LOGT":"127.04901373","CMPNM_NM":"쟈드헤어","TELNO":"031-878-3283","REFINE_LOTNO_ADDR":"경기도 의정부시 호원동 462-35번지 2층","INDUTYPE_NM":"보건위생 - 미용원"},{"REFINE_WGS84_LAT":"37.725542843","REFINE_WGS84_LOGT":"127.04907063","CMPNM_NM":"정원미용실","TELNO":"031-875-2927","REFINE_LOTNO_ADDR":"경기도 의정부시 호원동 423-5번지","INDUTYPE_NM":"보건위생 - 미용원"},{"REFINE_WGS84_LAT":"37.728734354","REFINE_WGS84_LOGT":"127.04329878","CMPNM_NM":"제이제이헤어","TELNO":"031-837-2581","REFINE_LOTNO_ADDR":"경기도 의정부시 호원동 326-1번지 102호","INDUTYPE_NM":"보건위생 - 미용원"},{"REFINE_WGS84_LAT":"37.72104847","REFINE_WGS84_LOGT":"127.04531354","CMPNM_NM":"제이헤어샵","TELNO":"031-837-9972","REFINE_LOTNO_ADDR":"경기도 의정부시 호원동 55-4번지 신일유토빌아파트 2동 103호","INDUTYPE_NM":"보건위생 - 미용원"},{"REFINE_WGS84_LAT":"37.727904633","REFINE_WGS84_LOGT":"127.04568043","CMPNM_NM":"종임스이쁜내머으리","TELNO":"031-837-3573","REFINE_LOTNO_ADDR":"경기도 의정부시 호원동 6-26번지 회룡빌딩 1층 4호","INDUTYPE_NM":"보건위생 - 미용원"},{"REFINE_WGS84_LAT":"37.720741216","REFINE_WGS84_LOGT":"127.04782","CMPNM_NM":"주가이헤어","TELNO":"031-875-7823","REFINE_LOTNO_ADDR":"경기도 의정부시 호원동 432-7번지 한주프라자 104호","INDUTYPE_NM":"보건위생 - 미용원"},{"REFINE_WGS84_LAT":"37.712903167","REFINE_WGS84_LOGT":"127.0470214","CMPNM_NM":"철수머리","TELNO":"031-825-0609","REFINE_LOTNO_ADDR":"경기도 의정부시 호원동 454-2번지 1층","INDUTYPE_NM":"보건위생 - 미용원"},{"REFINE_WGS84_LAT":"37.711208984","REFINE_WGS84_LOGT":"127.04801838","CMPNM_NM":"철수머리","TELNO":"031-826-7655","REFINE_LOTNO_ADDR":"경기도 의정부시 호원동 455-5번지 브랜드상설매장 108호","INDUTYPE_NM":"보건위생 - 미용원"},{"REFINE_WGS84_LAT":"37.730959197","REFINE_WGS84_LOGT":"127.04479737","CMPNM_NM":"카라헤어","TELNO":"031-111-2222","REFINE_LOTNO_ADDR":"경기도 의정부시 호원동 353-79번지 1층","INDUTYPE_NM":"보건위생 - 미용원"},{"REFINE_WGS84_LAT":"37.724651845","REFINE_WGS84_LOGT":"127.04657465","CMPNM_NM":"커커헤어","TELNO":"031-871-1400","REFINE_LOTNO_ADDR":"경기도 의정부시 호원동 51-1번지 3-1호","INDUTYPE_NM":"보건위생 - 미용원"},{"REFINE_WGS84_LAT":"37.72207581","REFINE_WGS84_LOGT":"127.04462223","CMPNM_NM":"코코헤어","TELNO":"031-824-8885","REFINE_LOTNO_ADDR":"경기도 의정부시 호원동 311-18번지 진원빌딩 103호","INDUTYPE_NM":"보건위생 - 미용원"},{"REFINE_WGS84_LAT":"37.727041502","REFINE_WGS84_LOGT":"127.04042802","CMPNM_NM":"텐 헤어","TELNO":"031-876-5396","REFINE_LOTNO_ADDR":"경기도 의정부시 호원동 339-13번지 107호","INDUTYPE_NM":"보건위생 - 미용원"},{"REFINE_WGS84_LAT":"37.707460708","REFINE_WGS84_LOGT":"127.04874189","CMPNM_NM":"토탈헤어","TELNO":"","REFINE_LOTNO_ADDR":"경기도 의정부시 호원동 463-4번지 1층 일부","INDUTYPE_NM":"보건위생 - 미용원"},{"REFINE_WGS84_LAT":"37.723958179","REFINE_WGS84_LOGT":"127.04638142","CMPNM_NM":"필헤어 의정부회룡점","TELNO":"031-877-3011","REFINE_LOTNO_ADDR":"경기도 의정부시 호원동 50-2번지 회룡타운 201호","INDUTYPE_NM":"보건위생 - 미용원"},{"REFINE_WGS84_LAT":"37.727733993","REFINE_WGS84_LOGT":"127.04416033","CMPNM_NM":"해피헤어","TELNO":"031-826-0088","REFINE_LOTNO_ADDR":"경기도 의정부시 호원동 340-11번지 1층","INDUTYPE_NM":"보건위생 - 미용원"},{"REFINE_WGS84_LAT":"37.703964881","REFINE_WGS84_LOGT":"127.04898921","CMPNM_NM":"헤라","TELNO":"031-875-0323","REFINE_LOTNO_ADDR":"경기도 의정부시 호원동 467번지 아이파크호원동 상가동 101호","INDUTYPE_NM":"보건위생 - 미용원"},{"REFINE_WGS84_LAT":"37.705127359","REFINE_WGS84_LOGT":"127.04837757","CMPNM_NM":"헤어디자인k","TELNO":"031-874-1588","REFINE_LOTNO_ADDR":"경기도 의정부시 호원동 466-10번지 1층","INDUTYPE_NM":"보건위생 - 미용원"},{"REFINE_WGS84_LAT":"37.728797222","REFINE_WGS84_LOGT":"127.04387733","CMPNM_NM":"헤어살롱 미휴","TELNO":"031-848-4090","REFINE_LOTNO_ADDR":"경기도 의정부시 호원동 326-27번지","INDUTYPE_NM":"보건위생 - 미용원"},{"REFINE_WGS84_LAT":"37.724346614","REFINE_WGS84_LOGT":"127.04351191","CMPNM_NM":"헤어스토리","TELNO":"031-875-0244","REFINE_LOTNO_ADDR":"경기도 의정부시 호원동 313-4번지 2층","INDUTYPE_NM":"보건위생 - 미용원"},{"REFINE_WGS84_LAT":"37.723463772","REFINE_WGS84_LOGT":"127.04322786","CMPNM_NM":"헤어장","TELNO":"031-837-5859","REFINE_LOTNO_ADDR":"경기도 의정부시 호원동 313-37번지 쌍용스윗닷홈 101동 1-06호","INDUTYPE_NM":"보건위생 - 미용원"},{"REFINE_WGS84_LAT":"37.715488353","REFINE_WGS84_LOGT":"127.04852","CMPNM_NM":"헤어카페1","TELNO":"031-874-5566","REFINE_LOTNO_ADDR":"경기도 의정부시 호원동 445-4번지","INDUTYPE_NM":"보건위생 - 미용원"},{"REFINE_WGS84_LAT":"37.715488353","REFINE_WGS84_LOGT":"127.04852","CMPNM_NM":"헤어카페1","TELNO":"","REFINE_LOTNO_ADDR":"경기도 의정부시 호원동 445-4번지","INDUTYPE_NM":"보건위생 - 미용원"},{"REFINE_WGS84_LAT":"37.722076014","REFINE_WGS84_LOGT":"127.04404377","CMPNM_NM":"헤어카페2","TELNO":"031-826-5565","REFINE_LOTNO_ADDR":"경기도 의정부시 호원동 309-8번지 1층","INDUTYPE_NM":"보건위생 - 미용원"},{"REFINE_WGS84_LAT":"37.712993263","REFINE_WGS84_LOGT":"127.04702145","CMPNM_NM":"헤어컬러블루","TELNO":"031-872-3809","REFINE_LOTNO_ADDR":"경기도 의정부시 호원동 454-1번지 1층","INDUTYPE_NM":"보건위생 - 미용원"},{"REFINE_WGS84_LAT":"37.727263628","REFINE_WGS84_LOGT":"127.04918513","CMPNM_NM":"헤어현주","TELNO":"070-767-2299","REFINE_LOTNO_ADDR":"경기도 의정부시 호원동 419번지 현대 상가 103호","INDUTYPE_NM":"보건위생 - 미용원"},{"REFINE_WGS84_LAT":"37.711208984","REFINE_WGS84_LOGT":"127.04801838","CMPNM_NM":"황예숙 헤어","TELNO":"031-829-2464","REFINE_LOTNO_ADDR":"경기도 의정부시 호원동 455-5번지 다매오 상가 1층 109호","INDUTYPE_NM":"보건위생 - 미용원"}]