[{"lat":"37.284382503","long":"127.45502157","imageIndex":8,"items":[{"name":"경희신한의원","tel":"031-634-1175","addr":"경기도 이천시 갈산동 601번지 스마트빌딩 1층 103-2호","indutype":"의원 - 한의원","category":"medical"}]},{"lat":"37.280768663","long":"127.45757084","imageIndex":8,"items":[{"name":"바른침한의원","tel":"031-633-1022","addr":"경기도 이천시 갈산동 716-1번지 주공프라자 204호","indutype":"의원 - 한의원","category":"medical"},{"name":"새서울의원","tel":"031-634-8277","addr":"경기도 이천시 갈산동 716-1번지 주공프라자 3층 303호","indutype":"의원 - 의원","category":"medical"},{"name":"참조은약국","tel":"031-631-5339","addr":"경기도 이천시 갈산동 716-1번지 주공프라자 1층 106호","indutype":"약국 - 약국","category":"medical"}]},{"lat":"37.285269315","long":"127.45638005","imageIndex":8,"items":[{"name":"이솜치과","tel":"031-632-8080","addr":"경기도 이천시 갈산동 592-35번지 1층2층","indutype":"의원 - 치과의원","category":"medical"}]},{"lat":"37.284021285","long":"127.45523366","imageIndex":8,"items":[{"name":"이천365의원","tel":"031-636-3650","addr":"경기도 이천시 갈산동 602번지 1층 102호","indutype":"의원 - 의원","category":"medical"},{"name":"하나약국","tel":"031-634-9399","addr":"경기도 이천시 갈산동 602번지","indutype":"약국 - 약국","category":"medical"}]}]